ezelf/__init__.py
ezelf/__main__.py
ezelf/main.py
ezelf/sync/__init__.py
ezelf/sync/ezpie.py
ezelf-0.1.1.dist-info/METADATA
ezelf-0.1.1.dist-info/WHEEL
ezelf-0.1.1.dist-info/entry_points.txt
ezelf-0.1.1.dist-info/licenses/LICENSE
ezelf-0.1.1.dist-info/RECORD
