Metadata-Version: 2.1
Name: ezelf
Version: 0.1.1
Summary: A elf for ezpie
License: MIT License
License-File: LICENSE
Classifier: License :: OSI Approved :: MIT License
Classifier: Operating System :: OS Independent
Classifier: Programming Language :: Python :: 3
Requires-Python: >=3.7
Requires-Dist: cos-python-sdk-v5
Requires-Dist: requests
Requires-Dist: typer[all]
